<?xml version="1.0" encoding="UTF-8"?>
<MF0 version="1.1" packageUris="http://schema.mathworks.com/mf0/sl_modelref_info/R2019a">
  <ModelRefInfoRepo.ModelRefInfoRoot type="ModelRefInfoRepo.ModelRefInfoRoot" uuid="1965edea-6049-4644-9a5b-025ec2b2f443">
    <autoSolverStatusFlags>323</autoSolverStatusFlags>
    <childModelRefInfo type="ModelRefInfoRepo.ChildModelRefInfo" uuid="2d05c24d-8579-4728-9c0c-2b9e5d798dbb">
      <isSingleInstance>true</isSingleInstance>
      <modelName>flightController</modelName>
      <modelPath>flightController</modelPath>
    </childModelRefInfo>
    <dataTransferInfos>AAFJTQAAAAAOAAAAOAAAAAYAAAAIAAAAAgAAAAAAAAAFAAAACAAAAAAAAAABAAAAAQAAAAAAAAAFAAQAAQAAAAEAAAAAAAAA</dataTransferInfos>
    <fundamentalSampleTimePeriod>0.0050000000000000001</fundamentalSampleTimePeriod>
    <globalVariables>CommandBus</globalVariables>
    <globalVariables>Controller</globalVariables>
    <globalVariables>D_pr</globalVariables>
    <globalVariables>D_xy</globalVariables>
    <globalVariables>D_yaw</globalVariables>
    <globalVariables>D_z</globalVariables>
    <globalVariables>I_pr</globalVariables>
    <globalVariables>I_pr_antiWU</globalVariables>
    <globalVariables>I_pr_satLimitHigh</globalVariables>
    <globalVariables>I_pr_satLimitLow</globalVariables>
    <globalVariables>P_pr</globalVariables>
    <globalVariables>P_xy</globalVariables>
    <globalVariables>P_yaw</globalVariables>
    <globalVariables>P_z</globalVariables>
    <globalVariables>TFinal</globalVariables>
    <globalVariables>Ts</globalVariables>
    <globalVariables>Vehicle</globalVariables>
    <globalVariables>g</globalVariables>
    <globalVariables>statesEstim_t</globalVariables>
    <hasBlockWithPeriodicDiscreteSampleTime>true</hasBlockWithPeriodicDiscreteSampleTime>
    <hasBwsAccessed>true</hasBwsAccessed>
    <hasBwsAccessedByAnyModel>true</hasBwsAccessedByAnyModel>
    <hasNonVirtualConstantTs>true</hasNonVirtualConstantTs>
    <inlinedVariables>Controller</inlinedVariables>
    <inlinedVariables>D_pr</inlinedVariables>
    <inlinedVariables>D_xy</inlinedVariables>
    <inlinedVariables>D_yaw</inlinedVariables>
    <inlinedVariables>D_z</inlinedVariables>
    <inlinedVariables>I_pr</inlinedVariables>
    <inlinedVariables>I_pr_antiWU</inlinedVariables>
    <inlinedVariables>I_pr_satLimitHigh</inlinedVariables>
    <inlinedVariables>I_pr_satLimitLow</inlinedVariables>
    <inlinedVariables>P_pr</inlinedVariables>
    <inlinedVariables>P_xy</inlinedVariables>
    <inlinedVariables>P_yaw</inlinedVariables>
    <inlinedVariables>P_z</inlinedVariables>
    <inlinedVariables>TFinal</inlinedVariables>
    <inlinedVariables>Ts</inlinedVariables>
    <inlinedVariables>Vehicle</inlinedVariables>
    <inlinedVariables>g</inlinedVariables>
    <inports type="ModelRefInfoRepo.InportInformation" uuid="7bb5651e-0cec-447f-9972-432f144d99fd">
      <isNotDerivPort>true</isNotDerivPort>
      <designMax>inf</designMax>
      <designMin>-inf</designMin>
      <indexType>2</indexType>
      <rateInfo type="ModelRefInfoRepo.RateInfo">
        <compiled>true</compiled>
        <nonFcnCallPartitionName>D1</nonFcnCallPartitionName>
        <period>0.0050000000000000001</period>
        <priority>40</priority>
        <rateIdx>0</rateIdx>
      </rateInfo>
      <resolvedSignalObject></resolvedSignalObject>
      <sigNameToEMVCEMap type="ModelRefInfoRepo.SigNameEMVCEInfo" uuid="33c2c3ae-6a15-45fb-845d-298877581e2c"/>
    </inports>
    <inports type="ModelRefInfoRepo.InportInformation" uuid="f58bef1f-b4e7-4f77-90a9-21e41598eb4d">
      <isNotDerivPort>true</isNotDerivPort>
      <designMax>inf</designMax>
      <designMin>-inf</designMin>
      <indexType>2</indexType>
      <originalPortNumber>1</originalPortNumber>
      <rateInfo type="ModelRefInfoRepo.RateInfo">
        <compiled>true</compiled>
        <nonFcnCallPartitionName>D1</nonFcnCallPartitionName>
        <period>0.0050000000000000001</period>
        <priority>40</priority>
        <rateIdx>0</rateIdx>
      </rateInfo>
      <resolvedSignalObject></resolvedSignalObject>
      <sigNameToEMVCEMap type="ModelRefInfoRepo.SigNameEMVCEInfo" uuid="437bef8d-e2fc-4830-98a5-c39c8319607c"/>
    </inports>
    <isInlineParamsOn>true</isInlineParamsOn>
    <isNumAllowedInstancesOne>true</isNumAllowedInstancesOne>
    <isOrigInportVirtualBus>false</isOrigInportVirtualBus>
    <isOrigInportVirtualBus>false</isOrigInportVirtualBus>
    <isOrigOutportVirtualBus>false</isOrigOutportVirtualBus>
    <isOrigOutportVirtualBus>false</isOrigOutportVirtualBus>
    <isPreCompSingleRate>false</isPreCompSingleRate>
    <isRefModelConstant>false</isRefModelConstant>
    <loggingSaveFormat>4</loggingSaveFormat>
    <maxFreqHz>-1</maxFreqHz>
    <origInportBusType>CommandBus</origInportBusType>
    <origInportBusType>statesEstim_t</origInportBusType>
    <origOutportBusType></origOutportBusType>
    <origOutportBusType></origOutportBusType>
    <outports type="ModelRefInfoRepo.OutportInformation" uuid="5fabf0ba-9e2f-49e8-af3f-ef31620cb75a">
      <designMax>inf</designMax>
      <designMin>-inf</designMin>
      <indexType>2</indexType>
      <rateInfo type="ModelRefInfoRepo.RateInfo">
        <compiled>true</compiled>
        <nonFcnCallPartitionName>D1</nonFcnCallPartitionName>
        <period>0.0050000000000000001</period>
        <priority>40</priority>
        <rateIdx>0</rateIdx>
      </rateInfo>
      <resolvedSignalObject></resolvedSignalObject>
      <sigNameToEMVCEMap type="ModelRefInfoRepo.SigNameEMVCEInfo" uuid="58a25b00-a57f-41b4-b69d-dd71e38b26b6"/>
    </outports>
    <outports type="ModelRefInfoRepo.OutportInformation" uuid="038e30b0-0361-4ae8-9501-5cc4e74f0d8f">
      <designMax>inf</designMax>
      <designMin>-inf</designMin>
      <indexType>2</indexType>
      <originalPortNumber>1</originalPortNumber>
      <rateInfo type="ModelRefInfoRepo.RateInfo">
        <compiled>true</compiled>
        <nonFcnCallPartitionName>D1</nonFcnCallPartitionName>
        <period>0.0050000000000000001</period>
        <priority>40</priority>
        <rateIdx>0</rateIdx>
      </rateInfo>
      <resolvedSignalObject></resolvedSignalObject>
      <sigNameToEMVCEMap type="ModelRefInfoRepo.SigNameEMVCEInfo" uuid="64035055-5995-464c-8643-88834af493a5"/>
    </outports>
    <preCompAllowConstTsOnPorts>false</preCompAllowConstTsOnPorts>
    <preCompAllowPortBasedInTriggeredSS>false</preCompAllowPortBasedInTriggeredSS>
    <runtimeNonFcnCallRateInfos type="ModelRefInfoRepo.RateInfo">
      <compiled>true</compiled>
      <nonFcnCallPartitionName>D1</nonFcnCallPartitionName>
      <period>0.0050000000000000001</period>
      <priority>40</priority>
      <rateIdx>0</rateIdx>
    </runtimeNonFcnCallRateInfos>
    <sampleTimeInheritanceRule>2</sampleTimeInheritanceRule>
    <timingAndTaskingRegistry>&lt;?xml version=&quot;1.0&quot;?&gt;
&lt;slexec_sto version=&quot;1.1&quot; packageUris=&quot;http://schema.mathworks.com/mf0/slexec_mm_sto/R2019a_201808021136&quot;&gt;
  &lt;sto.Registry type=&quot;sto.Registry&quot; uuid=&quot;dc205101-e22a-4a05-8538-eb2d048cebfb&quot;&gt;
    &lt;clocks type=&quot;sto.Event&quot; uuid=&quot;732ede60-eed0-4575-bdf8-17a22a697cf2&quot;&gt;
      &lt;eventType&gt;UNSPECIFIED_EVENT_SOURCE&lt;/eventType&gt;
      &lt;cNum&gt;1&lt;/cNum&gt;
      &lt;clockType&gt;Event&lt;/clockType&gt;
      &lt;identifier&gt;NonTunableParameterChangeEvent&lt;/identifier&gt;
      &lt;resolution&gt;-1&lt;/resolution&gt;
      &lt;specifiedTaskingMode&gt;ExplicitTasking&lt;/specifiedTaskingMode&gt;
      &lt;timeAdvanceMode&gt;Unspecified&lt;/timeAdvanceMode&gt;
      &lt;clockDomain type=&quot;sto.ClockDomain&quot; uuid=&quot;1639afec-ac82-4222-9783-c05d2a20ea1a&quot;&gt;
        &lt;computedFundamentalStepSize&gt;-1&lt;/computedFundamentalStepSize&gt;
      &lt;/clockDomain&gt;
    &lt;/clocks&gt;
    &lt;clocks type=&quot;sto.Event&quot; uuid=&quot;f941debb-a31d-4aec-90b5-0d0115bd05f4&quot;&gt;
      &lt;eventType&gt;PARAMETER_CHANGE_EVENT&lt;/eventType&gt;
      &lt;cNum&gt;2&lt;/cNum&gt;
      &lt;clockType&gt;Event&lt;/clockType&gt;
      &lt;identifier&gt;ParameterChangeEvent&lt;/identifier&gt;
      &lt;resolution&gt;-1&lt;/resolution&gt;
      &lt;specifiedTaskingMode&gt;ExplicitTasking&lt;/specifiedTaskingMode&gt;
      &lt;timeAdvanceMode&gt;None&lt;/timeAdvanceMode&gt;
      &lt;clockDomain type=&quot;sto.ClockDomain&quot; uuid=&quot;82911714-4d36-4d3b-99ae-a545a78bd4a1&quot;&gt;
        &lt;computedFundamentalStepSize&gt;-1&lt;/computedFundamentalStepSize&gt;
        &lt;rates type=&quot;sto.Rate&quot; uuid=&quot;d5409a95-ce4c-4e96-b019-dd26246f94e1&quot;/&gt;
        &lt;rootTaskHierarchyElements type=&quot;sto.Task&quot; uuid=&quot;f8578ec8-05e5-4aaf-b397-8e95b7b87ae4&quot;&gt;
          &lt;isExplicit&gt;true&lt;/isExplicit&gt;
          &lt;rates type=&quot;sto.Rate&quot; uuid=&quot;d5409a95-ce4c-4e96-b019-dd26246f94e1&quot;&gt;
            &lt;eventSourceType&gt;PARAMETER_CHANGE_EVENT&lt;/eventSourceType&gt;
            &lt;rateIDX&gt;-1&lt;/rateIDX&gt;
            &lt;registry type=&quot;sto.Registry&quot; uuid=&quot;dc205101-e22a-4a05-8538-eb2d048cebfb&quot;/&gt;
            &lt;stringID&gt;ParameterChangeEvent&lt;/stringID&gt;
            &lt;taskId&gt;ModelWideParameterChangeEvent&lt;/taskId&gt;
            &lt;useForExecution&gt;NotForExecution&lt;/useForExecution&gt;
            &lt;rateSpec type=&quot;sto.RateSpec&quot; uuid=&quot;b4f5cc44-3874-480c-b26b-8b1ac84de219&quot;&gt;
              &lt;period&gt;inf&lt;/period&gt;
              &lt;rateType&gt;ModelWideParameterChangeEvent&lt;/rateType&gt;
            &lt;/rateSpec&gt;
          &lt;/rates&gt;
          &lt;tNum&gt;1&lt;/tNum&gt;
          &lt;timeKeeperClockID&gt;ParameterChangeEvent&lt;/timeKeeperClockID&gt;
          &lt;elementType&gt;Task&lt;/elementType&gt;
          &lt;identifier&gt;ModelWideParameterChangeEvent&lt;/identifier&gt;
          &lt;priority&gt;-1&lt;/priority&gt;
          &lt;schedulingClockID&gt;ParameterChangeEvent&lt;/schedulingClockID&gt;
        &lt;/rootTaskHierarchyElements&gt;
      &lt;/clockDomain&gt;
    &lt;/clocks&gt;
    &lt;clocks type=&quot;sto.Timer&quot; uuid=&quot;50d9bb50-759b-4d08-a78d-b6d334af7481&quot;&gt;
      &lt;needsToProvideTimeDuringExecution&gt;true&lt;/needsToProvideTimeDuringExecution&gt;
      &lt;clockTickConstraint&gt;PeriodicWithFixedResolution&lt;/clockTickConstraint&gt;
      &lt;resolution&gt;0.0050000000000000001&lt;/resolution&gt;
      &lt;specifiedTaskingMode&gt;ClassicMultiTasking&lt;/specifiedTaskingMode&gt;
      &lt;clockDomain type=&quot;sto.ClockDomain&quot; uuid=&quot;2d6a8da5-25f0-48a3-8ee9-5e52c9a83f10&quot;&gt;
        &lt;baseTaskID&gt;_task0&lt;/baseTaskID&gt;
        &lt;computedFundamentalStepSize&gt;0.0050000000000000001&lt;/computedFundamentalStepSize&gt;
        &lt;rates type=&quot;sto.Rate&quot; uuid=&quot;943ec0bd-fdc4-46c5-8ddd-1762d12c960f&quot;/&gt;
        &lt;rates type=&quot;sto.Rate&quot; uuid=&quot;2cd818c5-2211-4693-8ae2-558b66cf46eb&quot;/&gt;
        &lt;rootTaskHierarchyElements type=&quot;sto.Task&quot; uuid=&quot;0a430807-a891-40d5-85b7-baa808940bcf&quot;&gt;
          &lt;isExecutable&gt;true&lt;/isExecutable&gt;
          &lt;orderIndex&gt;1&lt;/orderIndex&gt;
          &lt;rates type=&quot;sto.Rate&quot; uuid=&quot;943ec0bd-fdc4-46c5-8ddd-1762d12c960f&quot;&gt;
            &lt;annotation&gt;FiM&lt;/annotation&gt;
            &lt;colorIndex&gt;8&lt;/colorIndex&gt;
            &lt;description&gt;Fixed in Minor Step&lt;/description&gt;
            &lt;eventSourceType&gt;UNSPECIFIED_EVENT_SOURCE&lt;/eventSourceType&gt;
            &lt;rateIDX&gt;-1&lt;/rateIDX&gt;
            &lt;registry type=&quot;sto.Registry&quot; uuid=&quot;dc205101-e22a-4a05-8538-eb2d048cebfb&quot;/&gt;
            &lt;taskId&gt;_task0&lt;/taskId&gt;
            &lt;useForExecution&gt;NotForExecution&lt;/useForExecution&gt;
            &lt;rateSpec type=&quot;sto.RateSpec&quot; uuid=&quot;c83e861a-2070-4ddc-a8c7-7933a1122d95&quot;&gt;
              &lt;offset&gt;1&lt;/offset&gt;
              &lt;rateType&gt;ZOHContinuous&lt;/rateType&gt;
            &lt;/rateSpec&gt;
          &lt;/rates&gt;
          &lt;rates type=&quot;sto.Rate&quot; uuid=&quot;2cd818c5-2211-4693-8ae2-558b66cf46eb&quot;&gt;
            &lt;annotation&gt;D1&lt;/annotation&gt;
            &lt;colorIndex&gt;2&lt;/colorIndex&gt;
            &lt;description&gt;Discrete 1&lt;/description&gt;
            &lt;eventSourceType&gt;UNSPECIFIED_EVENT_SOURCE&lt;/eventSourceType&gt;
            &lt;registry type=&quot;sto.Registry&quot; uuid=&quot;dc205101-e22a-4a05-8538-eb2d048cebfb&quot;/&gt;
            &lt;taskId&gt;_task0&lt;/taskId&gt;
            &lt;rateSpec type=&quot;sto.RateSpec&quot; uuid=&quot;f6a7b8b8-dffb-4e4b-b89f-2252cbc6b982&quot;&gt;
              &lt;period&gt;0.0050000000000000001&lt;/period&gt;
              &lt;rateType&gt;ClassicPeriodicDiscrete&lt;/rateType&gt;
            &lt;/rateSpec&gt;
          &lt;/rates&gt;
          &lt;elementType&gt;Task&lt;/elementType&gt;
          &lt;identifier&gt;_task0&lt;/identifier&gt;
          &lt;priority&gt;40&lt;/priority&gt;
        &lt;/rootTaskHierarchyElements&gt;
      &lt;/clockDomain&gt;
    &lt;/clocks&gt;
    &lt;executionSpec&gt;Undetermined&lt;/executionSpec&gt;
    &lt;taskDependencyGraph type=&quot;sto.SerializedTaskConnectionList&quot; uuid=&quot;f6cdb58b-abea-4d2e-9feb-602d7bfa2e43&quot;&gt;
      &lt;taskIdentifier&gt;_task0&lt;/taskIdentifier&gt;
    &lt;/taskDependencyGraph&gt;
    &lt;taskDependencyGraph type=&quot;sto.SerializedTaskConnectionList&quot; uuid=&quot;087f7199-36ca-4335-a010-b670e6fc2391&quot;&gt;
      &lt;clockIdentifier&gt;ParameterChangeEvent&lt;/clockIdentifier&gt;
      &lt;taskIdentifier&gt;ModelWideParameterChangeEvent&lt;/taskIdentifier&gt;
    &lt;/taskDependencyGraph&gt;
    &lt;taskPriorityDirection&gt;HighNumberLast&lt;/taskPriorityDirection&gt;
    &lt;taskingMode&gt;ClassicMultiTasking&lt;/taskingMode&gt;
    &lt;tasks type=&quot;sto.Task&quot; uuid=&quot;f8578ec8-05e5-4aaf-b397-8e95b7b87ae4&quot;/&gt;
    &lt;tasks type=&quot;sto.Task&quot; uuid=&quot;0a430807-a891-40d5-85b7-baa808940bcf&quot;/&gt;
  &lt;/sto.Registry&gt;
&lt;/slexec_sto&gt;</timingAndTaskingRegistry>
    <userSpecifiedFixedStepSize>0.0050000000000000001</userSpecifiedFixedStepSize>
    <FMUBlockMap type="ModelRefInfoRepo.FMUBlockInfo" uuid="6d31f2d6-2e45-412b-b481-7dd1c96f221b"/>
    <codeGenInfo type="ModelRefInfoRepo.CodeGenInformation" uuid="c867ebb7-fb8b-4045-a8d5-1c11773a260a">
      <DWorkTypeName>MdlrefDW_flightController_T</DWorkTypeName>
    </codeGenInfo>
    <configSettingsForConsistencyChecks type="ModelRefInfoRepo.ConfigSettingsForConsistencyChecks" uuid="f5b73d9f-67a8-4c32-bd1c-434eadd8d814">
      <consistentOutportInitialization>true</consistentOutportInitialization>
      <fixedStepSize>0.0050000000000000001</fixedStepSize>
      <frameDiagnosticSetting>2</frameDiagnosticSetting>
      <hasHybridSampleTime>true</hasHybridSampleTime>
      <signalLoggingSaveFormat>2</signalLoggingSaveFormat>
      <solverName>FixedStepDiscrete</solverName>
      <solverType>SOLVER_TYPE_FIXEDSTEP</solverType>
      <hardwareSettings type="ModelRefInfoRepo.HardwareSettings" uuid="9f176707-b7db-4e3b-b289-364bc446a136">
        <prodBitPerChar>8</prodBitPerChar>
        <prodBitPerDouble>64</prodBitPerDouble>
        <prodBitPerFloat>32</prodBitPerFloat>
        <prodBitPerInt>32</prodBitPerInt>
        <prodBitPerLong>32</prodBitPerLong>
        <prodBitPerLongLong>64</prodBitPerLongLong>
        <prodBitPerPointer>32</prodBitPerPointer>
        <prodBitPerPtrDiffT>32</prodBitPerPtrDiffT>
        <prodBitPerShort>16</prodBitPerShort>
        <prodBitPerSizeT>32</prodBitPerSizeT>
        <prodEndianess>1</prodEndianess>
        <prodLargestAtomicInteger>3</prodLargestAtomicInteger>
        <prodShiftRight>true</prodShiftRight>
        <prodWordSize>32</prodWordSize>
      </hardwareSettings>
    </configSettingsForConsistencyChecks>
    <dataPortGroup type="ModelRefInfoRepo.DataPortGroup" uuid="69b6dcce-d577-4dc2-99a9-458643099061">
      <dataInputPorts>0</dataInputPorts>
      <dataInputPorts>1</dataInputPorts>
      <dataOutputPorts>0</dataOutputPorts>
      <dataOutputPorts>1</dataOutputPorts>
    </dataPortGroup>
    <interfaceParameterInfo type="ModelRefInfoRepo.InterfaceParameterInfo" uuid="1f50268a-6ef8-4414-917e-b4e28a49caa8"/>
    <messageInfo type="ModelRefInfoRepo.MessageInformation" uuid="e66d7aed-319c-43ab-a060-a743e16dee95"/>
    <methodInfo type="ModelRefInfoRepo.MethodExistenceInfo" uuid="6553bce3-6da5-4499-9a87-920f356e863d">
      <hasSystemInitializeMethod>true</hasSystemInitializeMethod>
      <hasSystemResetMethod>true</hasSystemResetMethod>
      <hasTerminateMethod>true</hasTerminateMethod>
      <hasUpdateMethod>true</hasUpdateMethod>
    </methodInfo>
    <periodicEventPortUnsupportedBlockInfo type="ModelRefInfoRepo.PeriodicEventPortUnsupportedBlockInfo" uuid="c7302df7-95bf-4f24-8f13-e5144533da2f"/>
    <portGroupsRequireSameRate type="ModelRefInfoRepo.PortGroupsRequireSameRate" uuid="6b1291fc-b9b5-45c4-9cf6-1d94f62928ed">
      <DSMPortGroups type="ModelRefInfoRepo.NameToPortGroupIdxVectMap" uuid="a1a1b5d4-ec41-468e-8bd8-e2daa038bfe8"/>
      <GlobalDSMPortGroups type="ModelRefInfoRepo.NameToPortGroupIdxVectMap" uuid="769c531b-4a37-4c14-a8a9-12cab314b19c"/>
      <mergedPortGroups type="ModelRefInfoRepo.NameToPortGroupIdxVectMap" uuid="0db6eea5-13ff-4593-8f84-eacc3065b9a1"/>
    </portGroupsRequireSameRate>
    <rateSpecOfGlobalDSMAccessedByDescExpFcnMdlMap type="ModelRefInfoRepo.GlobalDSMRateSpecMap" uuid="9877a2ac-6352-4be4-9e16-6e09cb1b824a"/>
    <simulinkFunctions type="ModelRefInfoRepo.SimulinkFunctions" uuid="df405c65-6a76-4154-99d1-4f766188a120">
      <compSimulinkFunctionCatalog></compSimulinkFunctionCatalog>
      <variantSimulinkFunctions type="ModelRefInfoRepo.VariantSimulinkFunctions" uuid="5ed9ac17-7c28-4643-b576-41e49f98d81f"/>
    </simulinkFunctions>
    <stateWriterToOwnerMap type="ModelRefInfoRepo.StateWriterInfo" uuid="1d4d299e-5b12-41f7-8a1c-07e87ca6c836"/>
  </ModelRefInfoRepo.ModelRefInfoRoot>
</MF0>